setup.py
SinaL2/SinaL2.py
SinaL2/__init__.py
SinaL2/connection.py
SinaL2/util.py
SinaL2.egg-info/PKG-INFO
SinaL2.egg-info/SOURCES.txt
SinaL2.egg-info/dependency_links.txt
SinaL2.egg-info/requires.txt
SinaL2.egg-info/top_level.txt
SinaL2.egg-info/zip-safe
SinaL2/Sina/Sina.py
SinaL2/Sina/Vendor.py
SinaL2/Sina/__init__.py
SinaL2/Sina/config.py
SinaL2/Sina/connection.py
SinaL2/Sina/const.py
SinaL2/Sina/util.py