Metadata-Version: 1.1
Name: SinaL2
Version: 0.3
Summary: A module from dHydra, for sina level2 data
Home-page: http://dHydra.org
Author: Wen Gu
Author-email: emptyset110@gmail.com
License: Apache Software License
Keywords: Sina,Level2
Platform: UNKNOWN
Classifier: License :: OSI Approved :: Apache Software License
Classifier: Programming Language :: Python
Classifier: Intended Audience :: Financial and Insurance Industry
Classifier: Operating System :: OS Independent
